{"name":"sneaker 1","price":10,"brand":"Nike","owned":true,"releaseDate":"2021-11-03","userId":"1","_id":"1"}
{"name":"test","brand":"Vans","price":20,"owned":true,"releaseDate":"21-10-2000","userId":"1","_id":"10"}
{"name":"test","brand":"Vans","price":20,"owned":true,"releaseDate":"21-10-2000","userId":"1","_id":"11"}
{"name":"test","brand":"Vans","price":20,"owned":true,"releaseDate":"21-10-2000","userId":"1","_id":"12"}
{"name":"test","brand":"Vans","price":20,"owned":true,"releaseDate":"21-10-2000","userId":"1","_id":"13"}
{"name":"test","brand":"Vans","price":20,"owned":true,"releaseDate":"21-10-2000","userId":"1","_id":"14"}
{"name":"test","brand":"Vans","price":20,"owned":true,"releaseDate":"21-10-2000","userId":"1","_id":"15"}
{"name":"test","brand":"Vans","price":20,"owned":true,"releaseDate":"21-10-2000","userId":"1","_id":"16"}
{"name":"test","brand":"Vans","price":20,"owned":true,"releaseDate":"21-10-2000","userId":"1","_id":"17"}
{"name":"test","brand":"Vans","price":20,"owned":true,"releaseDate":"21-10-2000","userId":"1","_id":"18"}
{"name":"test","brand":"Vans","price":20,"owned":true,"releaseDate":"21-10-2000","userId":"1","_id":"19"}
{"name":"sneaker 2","price":200,"brand":"Nike","owned":true,"releaseDate":"2021-11-03","userId":"1","_id":"2"}
{"name":"test","brand":"Vans","price":20,"owned":true,"releaseDate":"21-10-2000","userId":"1","_id":"20"}
{"name":"test","brand":"Vans","price":20,"owned":true,"releaseDate":"21-10-2000","userId":"1","_id":"21"}
{"name":"test","brand":"Vans","price":20,"owned":true,"releaseDate":"21-10-2000","userId":"1","_id":"22"}
{"name":"test","brand":"Vans","price":20,"owned":true,"releaseDate":"21-10-2000","userId":"1","_id":"23"}
{"name":"test","brand":"Vans","price":20,"owned":true,"releaseDate":"21-10-2000","userId":"1","_id":"24"}
{"name":"test","brand":"Vans","price":20,"owned":true,"releaseDate":"21-10-2000","userId":"1","_id":"25"}
{"name":"test","brand":"Vans","price":20,"owned":true,"releaseDate":"21-10-2000","userId":"1","_id":"26"}
{"name":"test","brand":"Vans","price":20,"owned":true,"releaseDate":"21-10-2000","userId":"1","_id":"27"}
{"name":"test","brand":"Vans","price":20,"owned":true,"releaseDate":"21-10-2000","userId":"1","_id":"28"}
{"name":"test","brand":"Vans","price":20,"owned":true,"releaseDate":"21-10-2000","userId":"1","_id":"29"}
{"name":"sneaker 3","price":300,"brand":"Nike","owned":true,"releaseDate":"2021-11-03","userId":"1","_id":"3"}
{"name":"test","brand":"Vans","price":20,"owned":true,"releaseDate":"21-10-2000","userId":"1","_id":"30"}
{"name":"test","brand":"Vans","price":20,"owned":true,"releaseDate":"21-10-2000","userId":"1","_id":"31"}
{"name":"sneaker 4","price":400,"brand":"nike","owned":true,"releaseDate":"2021-11-03",",userId":"1","_id":"4"}
{"name":"sneaker 5","price":500,"brand":"nike","owned":true,"releaseDate":"2021-11-03","userId":"2","_id":"5"}
{"name":"alt sneaker","price":20,"brand":"Nike","owned":false,"releaseDate":"2021-11-03","userId":"1","_id":"6"}
{"name":"still worling","price":200,"brand":"Nike","owned":false,"releaseDate":"21-10-2000","userId":"1","_id":"DiuGNLnojr3GzO6K"}
{"name":"only for b","price":10,"brand":"nike","owned":false,"releaseDate":"2021-11-03","userId":"2","_id":"YE5HwpCL3bCLHWiy"}
{"name":"only for b v2","price":100,"brand":"nike","owned":false,"releaseDate":"2021-11-03","userId":"2","_id":"ZHt9I15xO1s3XO7M"}
{"name":"brand new","brand":"Vans","price":20,"owned":true,"releaseDate":"21-10-2000","userId":"1","_id":"ZY5hJguMcCNqzJ5q"}
{"name":"newest","brand":"Adidas","price":100,"owned":false,"releaseDate":"21-10-2000","userId":"1","_id":"lTmtlr3c8tyKLf2O"}
{"_id":"rIYpRIKsx9yB70Yv","name":"incerc","price":20,"brand":"Adidas","owned":true,"releaseDate":"2021-11-03","userId":"1"}
{"_id":"wLYYry9wKg7EJeiV","name":"test offline","price":10,"brand":"Adidas","owned":true,"releaseDate":"2021-11-03","userId":"1"}
{"name":"sneaker 2","price":10,"brand":"Nike","owned":true,"releaseDate":"2021-11-03","userId":"1","_id":"1"}
{"_id":"1","name":"sneaker 3","brand":"Nike","price":10,"owned":true,"releaseDate":"2021-11-03","userId":"1"}
{"_id":"1","name":"sneaker 3","brand":"Nike","price":10,"owned":false,"releaseDate":"2021-11-03","userId":"1"}
{"_id":"1","name":"sneaker 3","brand":"Puma","price":100,"owned":true,"releaseDate":"2021-11-03","userId":"1"}
